{"points": [{"name": "monster spotted here", "latitude": 42.25, "longitude": -60.583333333333336}, {"name": "Montreal's boat hit reef here", "latitude": 27.5, "longitude": -72.25}, {"name": "Cunard's boat damaged here", "latitude": 45.61666666666667, "longitude": -15.2}, {"name": "5th Avenue, New York", "latitude": 40.766666666666666, "longitude": -73.95}, {"name": "Cape Horn", "latitude": -55.983333333333334, "longitude": -67.28333333333333}, {"name": "Crespo Island", "latitude": 32.666666666666664, "longitude": 167.83333333333334}, {"name": "Nuku Hiva", "latitude": -8.95, "longitude": -139.53333333333333}, {"name": "Dangerous islands", "latitude": -13.5, "longitude": -125.5}, {"name": "Viti island", "latitude": -17.733333333333334, "longitude": 178.0}, {"name": "Franch ship broke here", "latitude": -8.3, "longitude": 156.5}, {"name": "Torres strait", "latitude": -10.5, "longitude": 142.5}], "routes": [{"name": "AL", "points": [{"name": "", "latitude": -23.5, "longitude": 105.0}, {"name": "", "latitude": 0.0, "longitude": 110.0}, {"name": "", "latitude": 23.5, "longitude": 132.0}, {"name": "Last day", "latitude": 31.25, "longitude": 136.7}]}, {"name": "NAT", "points": [{"name": "", "latitude": 32.666666666666664, "longitude": 137.25}, {"name": "Hunting trip", "latitude": 32.666666666666664, "longitude": 167.83333333333334}, {"name": "", "latitude": 23.5, "longitude": -172.0}, {"name": "", "latitude": 0.0, "longitude": -142.0}, {"name": "", "latitude": -23.5, "longitude": -135.0}, {"name": "Viti island", "latitude": -17.733333333333334, "longitude": 178.0}, {"name": "", "latitude": -15.366666666666667, "longitude": 166.95}, {"name": "", "latitude": -16.066666666666666, "longitude": 164.53333333333333}, {"name": "", "latitude": -10.5, "longitude": 142.5}, {"name": "", "latitude": -10.0, "longitude": 135.0}, {"name": "", "latitude": -11.5, "longitude": 122.0}]}, {"name": "DI", "points": [{"name": "", "latitude": -13.5, "longitude": -125.5}, {"name": "", "latitude": -13.5, "longitude": -151.5}, {"name": "", "latitude": -23.833333333333332, "longitude": -151.5}, {"name": "", "latitude": -23.833333333333332, "longitude": -125.5}, {"name": "", "latitude": -13.5, "longitude": -125.5}]}]}